[
    {
        "domain": ".medium.com",
        "expirationDate": 1763731875.090116,
        "hostOnly": false,
        "httpOnly": false,
        "name": "_ga_7JY7T788PK",
        "path": "/",
        "sameSite": null,
        "secure": false,
        "session": false,
        "storeId": null,
        "value": "GS1.1.1729171752.18.1.1729171875.0.0.0"
    },
    {
        "domain": ".medium.com",
        "expirationDate": 1763731875.090479,
        "hostOnly": false,
        "httpOnly": false,
        "name": "_ga",
        "path": "/",
        "sameSite": null,
        "secure": false,
        "session": false,
        "storeId": null,
        "value": "GA1.1.511490646.1725250696"
    },
    {
        "domain": "medium.com",
        "expirationDate": 1729449979,
        "hostOnly": true,
        "httpOnly": false,
        "name": "_dd_s",
        "path": "/",
        "sameSite": "strict",
        "secure": false,
        "session": false,
        "storeId": null,
        "value": "rum=0&expire=1729449959876"
    },
    {
        "domain": ".medium.com",
        "expirationDate": 1729776672,
        "hostOnly": false,
        "httpOnly": false,
        "name": "tz",
        "path": "/",
        "sameSite": null,
        "secure": false,
        "session": false,
        "storeId": null,
        "value": "-420"
    },
    {
        "domain": ".medium.com",
        "expirationDate": 1729776672,
        "hostOnly": false,
        "httpOnly": false,
        "name": "pr",
        "path": "/",
        "sameSite": null,
        "secure": false,
        "session": false,
        "storeId": null,
        "value": "1"
    },
    {
        "domain": ".medium.com",
        "expirationDate": 1729776672,
        "hostOnly": false,
        "httpOnly": false,
        "name": "sz",
        "path": "/",
        "sameSite": null,
        "secure": false,
        "session": false,
        "storeId": null,
        "value": "1903"
    },
    {
        "domain": ".medium.com",
        "expirationDate": 1755946772,
        "hostOnly": false,
        "httpOnly": false,
        "name": "__stripe_mid",
        "path": "/",
        "sameSite": "strict",
        "secure": true,
        "session": false,
        "storeId": null,
        "value": "97c308b8-0012-471e-b2da-3fbd530f30d91e3438"
    },
    {
        "domain": "medium.com",
        "expirationDate": 1729535457.669823,
        "hostOnly": true,
        "httpOnly": true,
        "name": "xsrf",
        "path": "/",
        "sameSite": "no_restriction",
        "secure": true,
        "session": false,
        "storeId": null,
        "value": "ec8bcd0450d6"
    },
    {
        "domain": ".medium.com",
        "hostOnly": false,
        "httpOnly": true,
        "name": "_cfuvid",
        "path": "/",
        "sameSite": "no_restriction",
        "secure": true,
        "session": true,
        "storeId": null,
        "value": "BkHjrTtL5Xhl4MS0xmAucA_wt9jSjbN01JPw8L2xQL4-1729449059508-0.0.1.1-604800000"
    },
    {
        "domain": ".medium.com",
        "expirationDate": 1763731872.685523,
        "hostOnly": false,
        "httpOnly": true,
        "name": "uid",
        "path": "/",
        "sameSite": "no_restriction",
        "secure": true,
        "session": false,
        "storeId": null,
        "value": "a9226a292cc8"
    },
    {
        "domain": ".medium.com",
        "expirationDate": 1758848384.375204,
        "hostOnly": false,
        "httpOnly": false,
        "name": "nonce",
        "path": "/",
        "sameSite": "no_restriction",
        "secure": true,
        "session": false,
        "storeId": null,
        "value": "ZxfLVQqq"
    },
    {
        "domain": ".medium.com",
        "expirationDate": 1763731872.685544,
        "hostOnly": false,
        "httpOnly": true,
        "name": "sid",
        "path": "/",
        "sameSite": "no_restriction",
        "secure": true,
        "session": false,
        "storeId": null,
        "value": "1:oeLn31Kj7EZhHzXkWAOg3dXAstXA+o3h8FRrUqDPlZHLZ+YJfur3xlmyPCIG7ArI"
    },
    {
        "domain": ".medium.com",
        "expirationDate": 1729776672,
        "hostOnly": false,
        "httpOnly": false,
        "name": "sign",
        "path": "/",
        "sameSite": null,
        "secure": false,
        "session": false,
        "storeId": null,
        "value": "6769455667466e5070687a594876344468713243724e7258662f4d54503352526e784779752f572b614a4c7848614a644f63476649574953414f586e6e446536"
    }
]